jasapp/__init__.py
jasapp/cli.py
jasapp/gemini_integration.py
jasapp/linter.py
jasapp/renderers.py
jasapp/scorer.py
jasapp/utils.py
jasapp/parser/__init__.py
jasapp/parser/dockerfile.py
jasapp/parser/exceptions.py
jasapp/parser/kubernetes.py
jasapp/rules/__init__.py
jasapp/rules/base_rule.py
jasapp/rules/dockerfile/__init__.py
jasapp/rules/dockerfile/performance/PERF0001.py
jasapp/rules/dockerfile/performance/PERF0002.py
jasapp/rules/dockerfile/performance/PERF0004.py
jasapp/rules/dockerfile/performance/PERF0005.py
jasapp/rules/dockerfile/performance/PERF0006.py
jasapp/rules/dockerfile/performance/__init__.py
jasapp/rules/dockerfile/security/SEC0001.py
jasapp/rules/dockerfile/security/SEC0002.py
jasapp/rules/dockerfile/security/SEC0003.py
jasapp/rules/dockerfile/security/SEC0004.py
jasapp/rules/dockerfile/security/SEC0005.py
jasapp/rules/dockerfile/security/SEC0006.py
jasapp/rules/dockerfile/security/SEC0011.py
jasapp/rules/dockerfile/security/SEC0012.py
jasapp/rules/dockerfile/security/SEC0013.py
jasapp/rules/dockerfile/security/SEC0014.py
jasapp/rules/dockerfile/security/SEC0015.py
jasapp/rules/dockerfile/security/SEC0016.py
jasapp/rules/dockerfile/security/SEC0017.py
jasapp/rules/dockerfile/security/SEC0018.py
jasapp/rules/dockerfile/security/SEC0019.py
jasapp/rules/dockerfile/security/SEC0020.py
jasapp/rules/dockerfile/security/SEC0021.py
jasapp/rules/dockerfile/security/SEC0022.py
jasapp/rules/dockerfile/security/SEC0023.py
jasapp/rules/dockerfile/security/SEC0024.py
jasapp/rules/dockerfile/security/SEC0025.py
jasapp/rules/dockerfile/security/SEC0026.py
jasapp/rules/dockerfile/security/SEC0027.py
jasapp/rules/dockerfile/security/SEC0028.py
jasapp/rules/dockerfile/security/SEC0029.py
jasapp/rules/dockerfile/security/__init__.py
jasapp/rules/dockerfile/syntax/STX0001.py
jasapp/rules/dockerfile/syntax/STX0002.py
jasapp/rules/dockerfile/syntax/STX0003.py
jasapp/rules/dockerfile/syntax/STX0004.py
jasapp/rules/dockerfile/syntax/STX0005.py
jasapp-0.2.1.dist-info/LICENSE
jasapp-0.2.1.dist-info/METADATA
jasapp-0.2.1.dist-info/WHEEL
jasapp-0.2.1.dist-info/entry_points.txt
jasapp-0.2.1.dist-info/top_level.txt
jasapp-0.2.1.dist-info/RECORD
