Metadata-Version: 2.2
Name: jasapp
Version: 0.2.1
Summary: A tool for linting Dockerfiles & Kubernetes manifests with scoring capabilities.
Home-page: https://gitlab.com/jassouline/jasapp
Author: Jordan Assouline
Author-email: jordan.assouline@hotmail.fr
Classifier: Programming Language :: Python :: 3
Classifier: License :: OSI Approved :: MIT License
Classifier: Operating System :: OS Independent
Requires-Python: >=3.11
License-File: LICENSE
Requires-Dist: pyyaml==6.0.1
Requires-Dist: setuptools==68.0.0
Requires-Dist: requests==2.28.2
Requires-Dist: pytest==8.3.4
Requires-Dist: flake8==7.1.1
Requires-Dist: email-validator==2.2.0
Requires-Dist: google-generativeai==0.8.4
Dynamic: author
Dynamic: author-email
Dynamic: classifier
Dynamic: description
Dynamic: description-content-type
Dynamic: home-page
Dynamic: requires-dist
Dynamic: requires-python
Dynamic: summary
